adel_majli_calculator/__init__.py
adel_majli_calculator/calculator.py
adel_majli_calculator/setup.py
adel_majli_calculator-0.1.0.dist-info/LICENSE
adel_majli_calculator-0.1.0.dist-info/METADATA
adel_majli_calculator-0.1.0.dist-info/WHEEL
adel_majli_calculator-0.1.0.dist-info/top_level.txt
adel_majli_calculator-0.1.0.dist-info/RECORD
