Metadata-Version: 2.1
Name: adel-majli-calculator
Version: 0.1.0
Summary: آلة حاسبة بسيطة لإجراء العمليات الحسابية الأساسية.
Home-page: https://github.com/adelmajli/simple-calculator
Author: عادل مجلي
Author-email: contact@adelmajli.com
License: UNKNOWN
Platform: UNKNOWN
Classifier: Programming Language :: Python :: 3
Classifier: License :: OSI Approved :: MIT License
Classifier: Operating System :: OS Independent
Requires-Python: >=3.6
License-File: LICENSE
